{
  "estorias": [
    {
      "id": 1,
      "nome": "Cadastrar usuários",
      "descricao": "Como administrador, quero cadastrar usuários no sistema.",
      "pontos": "20",
      "tarefas": []
    },
    {
      "id": 2,
      "nome": "Alterar usuários",
      "descricao": "Como administrador, quero alterar informações de usuários do sistema.",
      "pontos": "15",
      "tarefas": []
    },
    {
      "id": 3,
      "nome": "Excluir usuários",
      "descricao": "Como administrador, quero excluir usuários do sistema.",
      "pontos": "10",
      "tarefas": []
    }
  ]
}